{"api_combineurls.md":"8R44-5Sk","api_assignsymbols.md":"uMBrj4ug","api_castfunction.md":"xUOErC_p","api_parsejson_namespaces_parsejson.md":"JgSVFxjJ","api_maptree.md":"DcKcXjhe","api_index.md":"s5zpDZLv","api_sleep.md":"sSahMmQY","api_promisewithcontrol.md":"TKo3ppv6","api_objectcompact.md":"b0zPWn8M","api_filtertree.md":"mSclShWC","api_isabsoluteurl.md":"4XOLvDBz","api_totreearray.md":"ojXZGeZO","api_symbolsof.md":"2icsB_eW","api_parsejson_index.md":"mHl0JEjm","api_searchtree.md":"uhuoBW7Q","api_padzero.md":"F2tcsOut","api_getfullurl_index.md":"BrSpZ5DS","api_getfullurl_namespaces_getfullurl.md":"nSoDDCxx","api_createcallbacks_namespaces_createcallbacks.md":"SRoE6F-Z","api_createcallbacks_index.md":"25stWV_4","api_tree.md":"dvFVB21d","api_tovalue.md":"L2CTUd4o","api_timerwithcontrol.md":"KQbVU2Ws","api_casterror.md":"n6OqcULg","api_batchunset.md":"s-8SkWub","api_eachtree.md":"fRvw8bXF","api_pascalcase.md":"EdTu3vnP","guide_installation.md":"tr53PuMo","guide_quick-start.md":"3PCeFmgk","api_assignown.md":"GYPsAsNA","api_createswitch.md":"XvH2P5CX","api_isclient.md":"AHG12jIQ","api_findtree.md":"LBPhPLgR","index.md":"6gro7VfE","api_protoof.md":"kYIte4Fq","api_toarraytree.md":"gmuOjjCW"}
